satisfactory_save_reader/__init__.py
satisfactory_save_reader/bin_file.py
satisfactory_save_reader/data_file.py
satisfactory_save_reader/file.py
satisfactory_save_reader/save_reader.py
satisfactory_save_reader/utils.py
satisfactory_save_reader/zlib_file.py
satisfactory_save_reader-0.8.2.dist-info/LICENSE
satisfactory_save_reader-0.8.2.dist-info/METADATA
satisfactory_save_reader-0.8.2.dist-info/WHEEL
satisfactory_save_reader-0.8.2.dist-info/top_level.txt
satisfactory_save_reader-0.8.2.dist-info/RECORD
