Metadata-Version: 2.1
Name: satisfactory-save-reader
Version: 0.8.2
Summary: Package to parse a Satisfactory save file
Author-email: Forthwind <kl.forthwind@gmail.com>
Project-URL: Homepage, https://github.com/klforthwind/SatisfactorySaveReader
Project-URL: Issues, https://github.com/klforthwind/SatisfactorySaveReader/issues
Classifier: Programming Language :: Python :: 3
Classifier: License :: OSI Approved :: GNU General Public License v3 (GPLv3)
Classifier: Operating System :: OS Independent
Requires-Python: >=3.8
License-File: LICENSE
